civilutils/__init__.py
civilutils/indian_standards/concrete.py
civilutils-0.1.1.dist-info/licenses/LICENSE
civilutils-0.1.1.dist-info/METADATA
civilutils-0.1.1.dist-info/WHEEL
civilutils-0.1.1.dist-info/top_level.txt
civilutils-0.1.1.dist-info/RECORD
