Metadata-Version: 2.4
Name: civilutils
Version: 0.1.1
Summary: Utilities for civil engineering: concrete mix design, material-property calculators, unit conversions, and common structural helpers for analysis and design workflows.
Author-email: Arumugam Maharaja <raja1998civil@gmail.com>
License: MIT
Project-URL: Homepage, https://github.com/amrajacivil/civilutils
Project-URL: Documentation, https://civilutils.readthedocs.io/en/latest/
Project-URL: Developer, https://amraja.in/
Keywords: civil,india,mixdesign,civil engineering,concrete,concrete mixdesign
Classifier: Development Status :: 4 - Beta
Classifier: Intended Audience :: Developers
Classifier: Intended Audience :: Science/Research
Classifier: Intended Audience :: End Users/Desktop
Classifier: Intended Audience :: Information Technology
Classifier: Intended Audience :: Other Audience
Classifier: Programming Language :: Python :: 3
Classifier: Operating System :: Unix
Classifier: Operating System :: MacOS
Classifier: Operating System :: Microsoft :: Windows
Requires-Python: >=3.9
License-File: LICENSE
Dynamic: license-file
